PySynonym-0.0.2.dist-info/top_level.txt
PySynonym-0.0.2.dist-info/METADATA
PySynonym-0.0.2.dist-info/metadata.json
PySynonym-0.0.2.dist-info/WHEEL
PySynonym-0.0.2.dist-info/RECORD
PySynonym-0.0.2.dist-info/DESCRIPTION.rst
PySynonym/core.py
PySynonym/__init__.py
